datasets/__init__.py
datasets/cuad.py
datasets/dataset_utils.py
datasets/mvtec.py
datasets/squad.py
datasets/timeseries.py
experiments/__init__.py
experiments/get_explanations.py
experiments/summary.py
experiments/train.py
gtx-1.0.data/scripts/gtx
models/__init__.py
models/fastflow.py
models/models.py
my_openxai/__init__.py
my_openxai/wrapper.py
my_openxai/explainers/__init__.py
my_openxai/explainers/perturbation_methods.py
my_openxai/explainers/api/__init__.py
my_openxai/explainers/api/base_explainer.py
my_openxai/explainers/catalog/__init__.py
my_openxai/explainers/catalog/perturbation_methods.py
my_openxai/explainers/catalog/ebp/__init__.py
my_openxai/explainers/catalog/ebp/ebp.py
my_openxai/explainers/catalog/grad/__init__.py
my_openxai/explainers/catalog/grad/grad.py
my_openxai/explainers/catalog/input_x_gradient/__init__.py
my_openxai/explainers/catalog/input_x_gradient/input_x_gradient.py
my_openxai/explainers/catalog/integrated_gradients/__init__.py
my_openxai/explainers/catalog/integrated_gradients/integrated_gradients.py
my_openxai/explainers/catalog/lime/__init__.py
my_openxai/explainers/catalog/lime/lime.py
my_openxai/explainers/catalog/lime/lime_package/__init__.py
my_openxai/explainers/catalog/lime/lime_package/discretize.py
my_openxai/explainers/catalog/lime/lime_package/exceptions.py
my_openxai/explainers/catalog/lime/lime_package/explanation.py
my_openxai/explainers/catalog/lime/lime_package/lime_base.py
my_openxai/explainers/catalog/lime/lime_package/lime_image.py
my_openxai/explainers/catalog/lime/lime_package/lime_tabular.py
my_openxai/explainers/catalog/lime/lime_package/lime_text.py
my_openxai/explainers/catalog/lime/lime_package/submodular_pick.py
my_openxai/explainers/catalog/lime/lime_package/tests/__init__.py
my_openxai/explainers/catalog/lime/lime_package/tests/test_discretize.py
my_openxai/explainers/catalog/lime/lime_package/tests/test_generic_utils.py
my_openxai/explainers/catalog/lime/lime_package/tests/test_lime_tabular.py
gtx-1.0.dist-info/LICENSE
gtx-1.0.dist-info/METADATA
gtx-1.0.dist-info/WHEEL
gtx-1.0.dist-info/top_level.txt
gtx-1.0.dist-info/RECORD
