Metadata-Version: 2.1
Name: gtx
Version: 1.0
Summary: A Ground Truth eXplanation Dataset
Home-page: https://github.com/xjiae/HDDDS
Author: Xiayan Ji, Anton Xue
Author-email: xjiae@seas.upenn.edu
Classifier: Programming Language :: Python :: 3
Classifier: License :: OSI Approved :: MIT License
Classifier: Operating System :: OS Independent
License-File: LICENSE
